{
  "$schema": "https://srs.semanticops.com/schema/2.0/record.json",
  "instanceId": "b1000000-0000-4000-a000-000000000008",
  "typeId": "2a000013-0000-4000-a000-000000000013",
  "typeVersion": 2,
  "typeNamespace": "com.semanticops.spec",
  "typeName": "table",
  "fieldValues": [
    {
      "fieldId": "1a000025-0000-4000-a000-000000000025",
      "value": "**Relation category taxonomy:**"
    },
    {
      "fieldId": "1a000032-0000-4000-a000-000000000032",
      "entries": [
        {
          "value": "Category"
        },
        {
          "value": "Examples"
        }
      ]
    }
  ],
  "createdAt": "2026-05-27T00:00:00Z",
  "groupValues": [
    {
      "groupId": "rows",
      "entries": [
        {
          "fieldValues": [
            {
              "fieldId": "1a000033-0000-4000-a000-000000000033",
              "entries": [
                {
                  "value": "Composition"
                },
                {
                  "value": "`contains`, `part-of`, `has-section`"
                }
              ]
            }
          ]
        },
        {
          "fieldValues": [
            {
              "fieldId": "1a000033-0000-4000-a000-000000000033",
              "entries": [
                {
                  "value": "Refinement"
                },
                {
                  "value": "`refines`, `expands`, `summarises`"
                }
              ]
            }
          ]
        },
        {
          "fieldValues": [
            {
              "fieldId": "1a000033-0000-4000-a000-000000000033",
              "entries": [
                {
                  "value": "Dependency"
                },
                {
                  "value": "`depends-on`, `requires`, `blocks`, `enables`"
                }
              ]
            }
          ]
        },
        {
          "fieldValues": [
            {
              "fieldId": "1a000033-0000-4000-a000-000000000033",
              "entries": [
                {
                  "value": "Sequence"
                },
                {
                  "value": "`precedes`, `follows`, `overlaps`"
                }
              ]
            }
          ]
        },
        {
          "fieldValues": [
            {
              "fieldId": "1a000033-0000-4000-a000-000000000033",
              "entries": [
                {
                  "value": "Derivation"
                },
                {
                  "value": "`derived-from`, `extracted-from`, `based-on`"
                }
              ]
            }
          ]
        },
        {
          "fieldValues": [
            {
              "fieldId": "1a000033-0000-4000-a000-000000000033",
              "entries": [
                {
                  "value": "Evidence"
                },
                {
                  "value": "`evidences`, `supports`, `contradicts`"
                }
              ]
            }
          ]
        },
        {
          "fieldValues": [
            {
              "fieldId": "1a000033-0000-4000-a000-000000000033",
              "entries": [
                {
                  "value": "Governance"
                },
                {
                  "value": "`supersedes`, `amends`, `ratifies`, `delegates`"
                }
              ]
            }
          ]
        },
        {
          "fieldValues": [
            {
              "fieldId": "1a000033-0000-4000-a000-000000000033",
              "entries": [
                {
                  "value": "Association"
                },
                {
                  "value": "`relates-to`, `links-to`"
                }
              ]
            }
          ]
        }
      ]
    }
  ]
}
